apns_sdk_py/__init__.py
apns_sdk_py/api_async.py
apns_sdk_py/api_sync.py
apns_sdk_py/dt.py
apns_sdk_py-0.5.2.dist-info/WHEEL
apns_sdk_py-0.5.2.dist-info/METADATA
apns_sdk_py-0.5.2.dist-info/RECORD
