Metadata-Version: 2.1
Name: apns-sdk-py
Version: 0.5.2
Summary: QiYuTech APNs API Python SDK
Home-page: https://github.com/QiYuTechDev/apns_sdk_py
License: MIT
Author: dev
Author-email: dev@qiyutech.tech
Requires-Python: >=3.9,<4.0
Classifier: License :: OSI Approved :: MIT License
Classifier: Programming Language :: Python :: 3
Classifier: Programming Language :: Python :: 3.9
Requires-Dist: aiohttp (>=3.7,<4.0)
Requires-Dist: dataclasses-json (>=0.5,<0.6)
Requires-Dist: requests (>=2.25,<3)
Project-URL: Repository, https://github.com/QiYuTechDev/apns_sdk_py
